datasette_css_properties/__init__.py
datasette_css_properties-0.2.dist-info/METADATA
datasette_css_properties-0.2.dist-info/WHEEL
datasette_css_properties-0.2.dist-info/entry_points.txt
datasette_css_properties-0.2.dist-info/top_level.txt
datasette_css_properties-0.2.dist-info/RECORD
