Metadata-Version: 2.1
Name: datasette-css-properties
Version: 0.2
Summary: Experimental Datasette output plugin using CSS properties
Home-page: https://github.com/simonw/datasette-css-properties
Author: Simon Willison
License: Apache License, Version 2.0
Project-URL: Issues, https://github.com/simonw/datasette-css-properties/issues
Project-URL: CI, https://github.com/simonw/datasette-css-properties/actions
Project-URL: Changelog, https://github.com/simonw/datasette-css-properties/releases
Platform: UNKNOWN
Requires-Python: >=3.6
Requires-Dist: datasette
Provides-Extra: test
Requires-Dist: pytest ; extra == 'test'
Requires-Dist: pytest-asyncio ; extra == 'test'
